{
  "description": "MCS Warning Code 7",
  "plcVariableName": "MCS_Warning_Code_7",
  "mbUsed": true,
  "multiplier": 1,
  "addressOffset": 0,
  "mbRegister": 8017,
  "mbFunctionCode": 4,
  "mbUnit": "NoUnit",
  "mqttLowerLimit": -999999990.0,
  "mqttUpperLimit": 999999990.0,
  "mbScaling": 1.0,
  "mbOffset": 0.0,
  "mbType": "UINT16",
  "mbTypeSize": 16,
  "mqttScaling": 1.0,
  "mqttOffset": 0.0,
  "mqttUnit": "NoUnit",
  "mqttDecimals": 3,
  "mbHandler": 1,
  "mbHandlerOffset": 0,
  "mbIdx": 18
}